MANIFEST.in
README.rst
setup.cfg
setup.py
listwise/ListWise.py
listwise/SimpleSQLite3.py
listwise/__init__.py
listwise/config.py
listwise/db.py
listwise.egg-info/PKG-INFO
listwise.egg-info/SOURCES.txt
listwise.egg-info/dependency_links.txt
listwise.egg-info/requires.txt
listwise.egg-info/top_level.txt