Metadata-Version: 1.1
Name: listwise
Version: 1.0.4
Summary: ListWise.com email validation wrapper.
Home-page: https://github.com/zbarge/listwise.git
Author: Zeke Barge
Author-email: zekebarge@gmail.com
License: Apache Software License
Keywords: email validation parsing cleaning cleansing
Platform: any
Classifier: Programming Language :: Python
Classifier: Development Status :: 4 - Beta
Classifier: Natural Language :: English
Classifier: Environment :: Web Environment
Classifier: Intended Audience :: Developers
Classifier: License :: OSI Approved :: Apache Software License
Classifier: Operating System :: OS Independent
Classifier: Topic :: Software Development :: Libraries :: Python Modules
Classifier: Topic :: Software Development :: Libraries :: Application Frameworks
Classifier: Topic :: Internet :: WWW/HTTP :: Dynamic Content
